[
  {
    "title": "Gattaca",
    "year": 1997,
    "cast": [
      "Ethan Hawke",
      "Uma Thurman",
      "Jude Law"
    ],
    "genres": [
      "Science Fiction"
    ]
  },
  {
    "title": "George Wallace",
    "year": 1997,
    "cast": [
      "Gary Sinise",
      "Mare Winningham",
      "Angelina Jolie"
    ],
    "genres": [
      "Biography"
    ]
  },
  {
    "title": "George of the Jungle",
    "year": 1997,
    "cast": [
      "Brendan Fraser",
      "Leslie Mann",
      "Thomas Haden Church"
    ],
    "genres": [
      "Comedy"
    ]
  },
  {
    "title": "Geri's Game",
    "year": 1997,
    "cast": [],
    "genres": [
      "Animated",
      "Short"
    ]
  },
  {
    "title": "Get a Clue",
    "year": 1997,
    "cast": [
      "Ray Walston",
      "Diane Ladd",
      "Sally Kirkland"
    ],
    "genres": [
      "Family"
    ]
  },
  {
    "title": "Ghosts",
    "year": 1997,
    "cast": [
      "Michael Jackson"
    ],
    "genres": []
  },
  {
    "title": "Going All the Way",
    "year": 1997,
    "cast": [
      "Jeremy Davis",
      "Ben Affleck",
      "Amy Locane"
    ],
    "genres": [
      "Drama"
    ]
  },
  {
    "title": "Gone Fishin'",
    "year": 1997,
    "cast": [
      "Joe Pesci",
      "Danny Glover",
      "Rosanna Arquette",
      "Lynn Whitfield"
    ],
    "genres": [
      "Comedy"
    ]
  },
  {
    "title": "Good Burger",
    "year": 1997,
    "cast": [
      "Kenan Thompson",
      "Kel Mitchell"
    ],
    "genres": [
      "Comedy"
    ]
  },
  {
    "title": "Good Will Hunting",
    "year": 1997,
    "cast": [
      "Matt Damon",
      "Robin Williams",
      "Ben Affleck",
      "Minnie Driver",
      "Stellan Skarsgård"
    ],
    "genres": [
      "Drama"
    ]
  },
  {
    "title": "Goodbye America",
    "year": 1997,
    "cast": [
      "Wolfgang Bodison",
      "Corin Nemec"
    ],
    "genres": [
      "Action"
    ]
  },
  {
    "title": "Grateful Dead: Downhill from Here",
    "year": 1997,
    "cast": [
      "The Grateful Dead"
    ],
    "genres": [
      "Performance"
    ]
  },
  {
    "title": "Gridlock'd",
    "year": 1997,
    "cast": [
      "Tim Roth",
      "Tupac Shakur"
    ],
    "genres": [
      "Comedy",
      "Crime"
    ]
  },
  {
    "title": "Grosse Pointe Blank",
    "year": 1997,
    "cast": [
      "John Cusack",
      "Minnie Driver",
      "Dan Aykroyd",
      "Alan Arkin"
    ],
    "genres": [
      "Comedy"
    ]
  },
  {
    "title": "Hacks",
    "year": 1997,
    "cast": [
      "Stephen Rea",
      "Illeana Douglas",
      "John Ritter"
    ],
    "genres": [
      "Comedy"
    ]
  },
  {
    "title": "Hands on a Hard Body: The Documentary",
    "year": 1997,
    "cast": [],
    "genres": [
      "Documentary"
    ]
  },
  {
    "title": "Hard Eight",
    "year": 1997,
    "cast": [
      "Philip Baker Hall",
      "John C. Reilly",
      "Gwyneth Paltrow"
    ],
    "genres": [
      "Drama"
    ]
  },
  {
    "title": "Hav Plenty",
    "year": 1997,
    "cast": [],
    "genres": [
      "Comedy"
    ]
  },
  {
    "title": "Henry Fool",
    "year": 1997,
    "cast": [
      "Thomas Jay Ryan",
      "Parker Posey"
    ],
    "genres": [
      "Drama"
    ]
  },
  {
    "title": "Hercules",
    "year": 1997,
    "cast": [],
    "genres": [
      "Family",
      "Fantasy"
    ]
  },
  {
    "title": "Highball",
    "year": 1997,
    "cast": [
      "Justine Bateman",
      "Peter Bogdanovich"
    ],
    "genres": [
      "Comedy"
    ]
  },
  {
    "title": "Hitler",
    "year": 1997,
    "cast": [],
    "genres": []
  },
  {
    "title": "Home Alone 3",
    "year": 1997,
    "cast": [
      "Alex D. Linz"
    ],
    "genres": [
      "Family"
    ]
  },
  {
    "title": "Honey, We Shrunk Ourselves",
    "year": 1997,
    "cast": [
      "Rick Moranis"
    ],
    "genres": [
      "Science Fiction"
    ]
  },
  {
    "title": "Hoodlum",
    "year": 1997,
    "cast": [
      "Laurence Fishburne",
      "Tim Roth",
      "Vanessa Williams",
      "Andy García"
    ],
    "genres": [
      "Crime"
    ]
  },
  {
    "title": "The House of Yes",
    "year": 1997,
    "cast": [
      "Parker Posey"
    ],
    "genres": [
      "Comedy"
    ]
  },
  {
    "title": "Hugo Pool",
    "year": 1997,
    "cast": [
      "Alyssa Milano",
      "Patrick Dempsey"
    ],
    "genres": [
      "Comedy"
    ]
  },
  {
    "title": "Hurricane Streets",
    "year": 1997,
    "cast": [
      "Heather Matarazzo"
    ],
    "genres": [
      "Drama"
    ]
  },
  {
    "title": "I Know What You Did Last Summer",
    "year": 1997,
    "cast": [
      "Jennifer Love Hewitt",
      "Sarah Michelle Gellar",
      "Ryan Phillippe",
      "Freddie Prinze, Jr.",
      "Johnny Galecki",
      "Bridgette Wilson",
      "Anne Heche"
    ],
    "genres": [
      "Horror"
    ]
  },
  {
    "title": "I Married a Strange Person!",
    "year": 1997,
    "cast": [],
    "genres": []
  },
  {
    "title": "I'm Bout It",
    "year": 1997,
    "cast": [
      "Master P"
    ],
    "genres": [
      "Drama"
    ]
  },
  {
    "title": "The Ice Storm",
    "year": 1997,
    "cast": [
      "Kevin Kline",
      "Joan Allen",
      "Sigourney Weaver",
      "Tobey Maguire",
      "Christina Ricci",
      "Elijah Wood"
    ],
    "genres": [
      "Drama"
    ]
  },
  {
    "title": "In & Out",
    "year": 1997,
    "cast": [
      "Kevin Kline",
      "Joan Cusack",
      "Tom Selleck",
      "Matt Dillon",
      "Bob Newhart",
      "Debbie Reynolds",
      "Wilford Brimley"
    ],
    "genres": [
      "Comedy"
    ]
  },
  {
    "title": "In the Company of Men",
    "year": 1997,
    "cast": [
      "Aaron Eckhart",
      "Matt Molloy"
    ],
    "genres": [
      "Comedy"
    ]
  },
  {
    "title": "In the Gloaming",
    "year": 1997,
    "cast": [
      "Glenn Close",
      "Bridget Fonda",
      "Whoopi Goldberg",
      "Robert Sean Leonard",
      "David Strathairn"
    ],
    "genres": [
      "Drama"
    ]
  },
  {
    "title": "Inferno",
    "year": 1997,
    "cast": [
      "Don Wilson"
    ],
    "genres": [
      "Action"
    ]
  },
  {
    "title": "The Informant",
    "year": 1997,
    "cast": [
      "Cary Elwes",
      "Timothy Dalton"
    ],
    "genres": [
      "Drama"
    ]
  },
  {
    "title": "Intensity",
    "year": 1997,
    "cast": [
      "Piper Laurie",
      "Molly Parker"
    ],
    "genres": [
      "Thriller"
    ]
  },
  {
    "title": "Inventing the Abbotts",
    "year": 1997,
    "cast": [
      "Liv Tyler",
      "Jennifer Connelly",
      "Joaquin Phoenix",
      "Billy Crudup",
      "Joanna Going"
    ],
    "genres": [
      "Comedy"
    ]
  },
  {
    "title": "It's In the Water",
    "year": 1997,
    "cast": [],
    "genres": [
      "Drama"
    ]
  },
  {
    "title": "The Jackal",
    "year": 1997,
    "cast": [
      "Bruce Willis",
      "Richard Gere",
      "Sidney Poitier",
      "Diane Venora"
    ],
    "genres": [
      "Thriller"
    ]
  },
  {
    "title": "Jackie Brown",
    "year": 1997,
    "cast": [
      "Pam Grier",
      "Samuel L. Jackson",
      "Robert Forster",
      "Robert De Niro",
      "Michael Keaton",
      "Bridget Fonda",
      "Chris Tucker"
    ],
    "genres": [
      "Crime",
      "Drama"
    ]
  },
  {
    "title": "Jane Eyre",
    "year": 1997,
    "cast": [
      "Samantha Morton",
      "Ciarán Hinds"
    ],
    "genres": [
      "Drama"
    ]
  },
  {
    "title": "Jungle 2 Jungle",
    "year": 1997,
    "cast": [
      "Tim Allen",
      "Martin Short",
      "JoBeth Williams",
      "Lolita Davidovich",
      "Sam Huntington"
    ],
    "genres": [
      "Comedy"
    ]
  },
  {
    "title": "Jungle Emperor Leo",
    "year": 1997,
    "cast": [],
    "genres": []
  },
  {
    "title": "Just in Time",
    "year": 1997,
    "cast": [
      "Mark Moses",
      "Brittany Alyse Smith"
    ],
    "genres": [
      "Romance",
      "Comedy"
    ]
  },
  {
    "title": "Just Write",
    "year": 1997,
    "cast": [
      "Sherilyn Fenn",
      "Jeremy Piven"
    ],
    "genres": [
      "Romance",
      "Comedy"
    ]
  },
  {
    "title": "Justice League of America",
    "year": 1997,
    "cast": [],
    "genres": [
      "Animated"
    ]
  },
  {
    "title": "Keeping the Promise",
    "year": 1997,
    "cast": [
      "Keith Carradine",
      "Annette O'Toole"
    ],
    "genres": [
      "Family",
      "Drama"
    ]
  },
  {
    "title": "Keys to Tulsa",
    "year": 1997,
    "cast": [
      "James Spader",
      "Eric Stoltz",
      "Mary Tyler Moore"
    ],
    "genres": [
      "Drama"
    ]
  },
  {
    "title": "Kiss the Girls",
    "year": 1997,
    "cast": [
      "Morgan Freeman",
      "Ashley Judd"
    ],
    "genres": [
      "Crime",
      "Thriller"
    ]
  },
  {
    "title": "Knockin' On Heaven's Door",
    "year": 1997,
    "cast": [
      "Rutger Hauer"
    ],
    "genres": []
  },
  {
    "title": "Kull the Conqueror",
    "year": 1997,
    "cast": [
      "Kevin Sorbo",
      "Tia Carrere",
      "Thomas Ian Griffith",
      "Litefoot",
      "Harvey Fierstein"
    ],
    "genres": [
      "Fantasy"
    ]
  },
  {
    "title": "Kundun",
    "year": 1997,
    "cast": [],
    "genres": [
      "Biography"
    ]
  },
  {
    "title": "L.A. Confidential",
    "year": 1997,
    "cast": [
      "Kevin Spacey",
      "Russell Crowe",
      "Guy Pearce",
      "Kim Basinger",
      "Danny DeVito",
      "James Cromwell",
      "David Strathairn",
      "Simon Baker"
    ],
    "genres": [
      "Crime",
      "Drama"
    ]
  },
  {
    "title": "The Land Before Time V: The Mysterious Island",
    "year": 1997,
    "cast": [],
    "genres": [
      "Animated"
    ]
  },
  {
    "title": "Last Stand at Saber River",
    "year": 1997,
    "cast": [
      "Tom Selleck",
      "Keith Carradine",
      "Haley Joel Osment"
    ],
    "genres": [
      "Western"
    ]
  },
  {
    "title": "The Last Time I Committed Suicide",
    "year": 1997,
    "cast": [
      "Thomas Jane",
      "Keanu Reeves"
    ],
    "genres": [
      "Drama"
    ]
  },
  {
    "title": "Latter-Day Saints",
    "year": 1997,
    "cast": [],
    "genres": []
  },
  {
    "title": "Lawn Dogs",
    "year": 1997,
    "cast": [
      "Sam Rockwell",
      "Mischa Barton",
      "Kathleen Quinlan"
    ],
    "genres": [
      "Drama"
    ]
  },
  {
    "title": "Leave It to Beaver",
    "year": 1997,
    "cast": [
      "Christopher McDonald",
      "Janine Turner"
    ],
    "genres": [
      "Family"
    ]
  },
  {
    "title": "Leprechaun 4: In Space",
    "year": 1997,
    "cast": [
      "Warwick Davis"
    ],
    "genres": [
      "Horror"
    ]
  },
  {
    "title": "Lewis and Clark and George",
    "year": 1997,
    "cast": [
      "Rose McGowan",
      "Dan Gunther"
    ],
    "genres": [
      "Comedy"
    ]
  },
  {
    "title": "Liar Liar",
    "year": 1997,
    "cast": [
      "Jim Carrey",
      "Justin Cooper",
      "Maura Tierney",
      "Cary Elwes",
      "Jennifer Tilly",
      "Amanda Donohoe"
    ],
    "genres": [
      "Comedy"
    ]
  },
  {
    "title": "Liberty!",
    "year": 1997,
    "cast": [
      "Roger Rees",
      "Philip Seymour Hoffman",
      "Donna Murphy"
    ],
    "genres": [
      "Documentary"
    ]
  },
  {
    "title": "A Life Less Ordinary",
    "year": 1997,
    "cast": [
      "Ewan McGregor",
      "Cameron Diaz",
      "Holly Hunter",
      "Delroy Lindo",
      "Ian Holm"
    ],
    "genres": [
      "Comedy"
    ]
  },
  {
    "title": "Little City",
    "year": 1997,
    "cast": [
      "Josh Charles",
      "Jon Bon Jovi",
      "Penelope Ann Miller"
    ],
    "genres": [
      "Romance",
      "Comedy"
    ]
  },
  {
    "title": "Little Red Riding Hood",
    "year": 1997,
    "cast": [],
    "genres": [
      "Short"
    ]
  },
  {
    "title": "Lolita",
    "year": 1997,
    "cast": [
      "Dominique Swain",
      "Jeremy Irons",
      "Frank Langella",
      "Melanie Griffith"
    ],
    "genres": [
      "Drama"
    ]
  },
  {
    "title": "Lost Highway",
    "year": 1997,
    "cast": [
      "Bill Pullman",
      "Patricia Arquette",
      "Balthazar Getty",
      "Robert Loggia",
      "Robert Blake"
    ],
    "genres": [
      "Suspense"
    ]
  },
  {
    "title": "The Lost World: Jurassic Park",
    "year": 1997,
    "cast": [
      "Jeff Goldblum",
      "Julianne Moore",
      "Pete Postlethwaite",
      "Arliss Howard",
      "Richard Attenborough"
    ],
    "genres": [
      "Science Fiction"
    ]
  },
  {
    "title": "Love Jones",
    "year": 1997,
    "cast": [
      "Larenz Tate",
      "Nia Long"
    ],
    "genres": [
      "Drama"
    ]
  },
  {
    "title": "Love and Death on Long Island",
    "year": 1997,
    "cast": [
      "John Hurt",
      "Jason Priestley"
    ],
    "genres": [
      "Drama"
    ]
  },
  {
    "title": "Love! Valour! Compassion!",
    "year": 1997,
    "cast": [
      "Jason Alexander",
      "John Glover"
    ],
    "genres": [
      "Drama"
    ]
  },
  {
    "title": "Lovelife",
    "year": 1997,
    "cast": [
      "Carla Gugino",
      "Sherilyn Fenn"
    ],
    "genres": [
      "Romance",
      "Comedy"
    ]
  },
  {
    "title": "Lucky Three",
    "year": 1997,
    "cast": [],
    "genres": [
      "Short"
    ]
  },
  {
    "title": "MPG: Motion Picture Genocide",
    "year": 1997,
    "cast": [],
    "genres": []
  },
  {
    "title": "Mad City",
    "year": 1997,
    "cast": [
      "Dustin Hoffman",
      "John Travolta",
      "Mia Kirshner",
      "Alan Alda"
    ],
    "genres": [
      "Crime",
      "Drama"
    ]
  },
  {
    "title": "The Man Who Knew Too Little",
    "year": 1997,
    "cast": [
      "Bill Murray",
      "Joanne Whalley",
      "Peter Gallagher"
    ],
    "genres": [
      "Comedy"
    ]
  },
  {
    "title": "Masterminds",
    "year": 1997,
    "cast": [
      "Patrick Stewart",
      "Vincent Kartheiser"
    ],
    "genres": [
      "Comedy"
    ]
  },
  {
    "title": "The MatchMaker",
    "year": 1997,
    "cast": [
      "Janeane Garofalo",
      "David O'Hara",
      "Milo O'Shea",
      "Denis Leary"
    ],
    "genres": [
      "Romance",
      "Comedy"
    ]
  },
  {
    "title": "McHale's Navy",
    "year": 1997,
    "cast": [
      "Tom Arnold",
      "Tim Curry",
      "David Alan Grier",
      "Debra Messing"
    ],
    "genres": [
      "Comedy"
    ]
  },
  {
    "title": "Mean Guns",
    "year": 1997,
    "cast": [
      "Ice-T",
      "Christopher Lambert"
    ],
    "genres": [
      "Crime",
      "Drama"
    ]
  },
  {
    "title": "Meet Wally Sparks",
    "year": 1997,
    "cast": [
      "Rodney Dangerfield",
      "Burt Reynolds",
      "Cindy Williams"
    ],
    "genres": [
      "Comedy"
    ]
  },
  {
    "title": "The Member of the Wedding",
    "year": 1997,
    "cast": [
      "Anna Paquin",
      "Alfre Woodard"
    ],
    "genres": [
      "Drama"
    ]
  },
  {
    "title": "Men in Black",
    "year": 1997,
    "cast": [
      "Will Smith",
      "Tommy Lee Jones",
      "Vincent D'Onofrio",
      "Linda Fiorentino",
      "Rip Torn",
      "Tony Shalhoub"
    ],
    "genres": [
      "Science Fiction"
    ]
  },
  {
    "title": "Men with Guns",
    "year": 1997,
    "cast": [
      "Mandy Patinkin"
    ],
    "genres": [
      "Drama"
    ]
  },
  {
    "title": "Metro",
    "year": 1997,
    "cast": [
      "Eddie Murphy",
      "Michael Wincott",
      "Michael Rapaport"
    ],
    "genres": [
      "Action"
    ]
  },
  {
    "title": "The Midas Touch",
    "year": 1997,
    "cast": [
      "Trever O'Brien"
    ],
    "genres": [
      "Fantasy"
    ]
  },
  {
    "title": "Midnight in the Garden of Good and Evil",
    "year": 1997,
    "cast": [
      "Kevin Spacey",
      "John Cusack",
      "Jude Law"
    ],
    "genres": [
      "Drama"
    ]
  },
  {
    "title": "Mighty Ducks the Movie: The First Face-Off",
    "year": 1997,
    "cast": [
      "voices of",
      "Brad Garrett",
      "James Belushi",
      "Tim Curry"
    ],
    "genres": [
      "Animated"
    ]
  },
  {
    "title": "Mimic",
    "year": 1997,
    "cast": [
      "Mira Sorvino",
      "Jeremy Northam",
      "Josh Brolin",
      "Charles S. Dutton",
      "Giancarlo Giannini",
      "F. Murray Abraham"
    ],
    "genres": [
      "Horror"
    ]
  },
  {
    "title": "Miss Evers' Boys",
    "year": 1997,
    "cast": [
      "Alfre Woodard",
      "Laurence Fishburne"
    ],
    "genres": [
      "Drama"
    ]
  },
  {
    "title": "Money Talks",
    "year": 1997,
    "cast": [
      "Chris Tucker",
      "Charlie Sheen",
      "Heather Locklear"
    ],
    "genres": [
      "Comedy"
    ]
  },
  {
    "title": "Monty Roberts: A Real Horse Whisperer",
    "year": 1997,
    "cast": [],
    "genres": [
      "Documentary"
    ]
  },
  {
    "title": "Mortal Kombat: Annihilation",
    "year": 1997,
    "cast": [
      "Robin Shou",
      "Talisa Soto",
      "Sandra Hess",
      "James Remar"
    ],
    "genres": [
      "Action"
    ]
  },
  {
    "title": "Most Wanted",
    "year": 1997,
    "cast": [
      "Keenen Ivory Wayans",
      "Jon Voight",
      "Jill Hennessy"
    ],
    "genres": [
      "Action"
    ]
  },
  {
    "title": "MouseHunt",
    "year": 1997,
    "cast": [
      "Nathan Lane",
      "Lee Evans",
      "Christopher Walken",
      "Maury Chaykin",
      "William Hickey"
    ],
    "genres": [
      "Comedy"
    ]
  },
  {
    "title": "Mr. Magoo",
    "year": 1997,
    "cast": [
      "Leslie Nielsen",
      "Miguel Ferrer",
      "Kelly Lynch",
      "Malcolm McDowell"
    ],
    "genres": [
      "Comedy"
    ]
  },
  {
    "title": "Mrs Dalloway",
    "year": 1997,
    "cast": [
      "Vanessa Redgrave",
      "Natascha McElhone"
    ],
    "genres": [
      "Drama"
    ]
  },
  {
    "title": "Murder at 1600",
    "year": 1997,
    "cast": [
      "Wesley Snipes",
      "Diane Lane"
    ],
    "genres": [
      "Thriller"
    ]
  }
]